pyspng/__init__.py
pyspng/_pyspng_c.cpython-310-x86_64-linux-gnu.so
pyspng/lib.py
pyspng/main.cpp
pyspng-0.1.4.dist-info/METADATA
pyspng-0.1.4.dist-info/WHEEL
pyspng-0.1.4.dist-info/RECORD
pyspng-0.1.4.dist-info/licenses/LICENSE
