Metadata-Version: 2.2
Name: pyspng
Version: 0.1.4
Summary: Fast libspng-based PNG decoder
Author-Email: Janne Hellsten <jjhellst@gmail.com>
Classifier: Development Status :: 4 - Beta
Classifier: License :: OSI Approved :: MIT License
Classifier: Programming Language :: Python :: 3 :: Only
Classifier: Programming Language :: Python :: 3.8
Classifier: Programming Language :: Python :: 3.9
Classifier: Programming Language :: Python :: 3.10
Classifier: Programming Language :: Python :: 3.11
Classifier: Programming Language :: Python :: 3.12
Project-URL: Homepage, https://github.com/nurpax/pyspng/
Project-URL: Documentation, https://pyspng.readthedocs.io/
Project-URL: Issues, https://github.com/nurpax/pyspng/issues
Requires-Python: >=3.7
Requires-Dist: numpy
Provides-Extra: test
Requires-Dist: pytest; extra == "test"
